nett/__init__.py
nett/example.py
nett_bd-0.0.3.dist-info/LICENSE
nett_bd-0.0.3.dist-info/METADATA
nett_bd-0.0.3.dist-info/WHEEL
nett_bd-0.0.3.dist-info/top_level.txt
nett_bd-0.0.3.dist-info/RECORD
